src/register_file.v
module register_file(
    input clk_i,
    input reset_i,
    input we3_i,
    input [4:0] a1_i,
    input [4:0] a2_i,
    input [4:0] a3_i,
    input [31:0] wd3_i,
    output reg [31:0] rd1_o,
    output reg [31:0] rd2_o
);
    reg [31:0] registers [31:0];
    reg [31:0] write_reg;
    always @(posedge clk_i, negedge reset_i) begin
        if (reset_i) begin
            for (integer i = 0; i<= 32; i++)
                registers[i] <= 32'd0;
        end
        else begin
            rd1_o <= (a1_i == 0) ? 32'd0 : registers[a1_i];
            rd2_o <= (a2_i == 0) ? 32'd0 : registers[a2_i];
            if ((a3_i != 32'd0) && we3_i)
                registers[a3_i] <= wd3_i;
        end
    end
endmodule

test/register_file_tb.v
`timescale 1ns / 1ps
`include "src/register_file.v"

module register_file_tb;
    reg clk_i;
    reg reset_i;
    reg we3_i;
    reg [4:0] a1_i;
    reg [4:0] a2_i;
    reg [4:0] a3_i;
    reg [31:0] wd3_i;
    wire [31:0] rd1_o;
    wire [31:0] rd2_o;

    register_file dut (
        .clk_i(clk_i),
        .reset_i(reset_i),
        .we3_i(we3_i),
        .a1_i(a1_i),
        .a2_i(a2_i),
        .a3_i(a3_i),
        .wd3_i(wd3_i),
        .rd1_o(rd1_o),
        .rd2_o(rd2_o)
    );

    initial begin
        $dumpfile("test/vcd/register_file.vcd");
        $dumpvars(0, register_file_tb);

        clk_i = 0;
        reset_i = 1;
        we3_i = 0;
        a1_i = 0;
        a2_i = 0;
        a3_i = 0;
        wd3_i = 0;
        
        // Reset
        #10 reset_i = 0;
        #10 reset_i = 1;

        // Test 1
        #10 a1_i = 1;  // Read register 1
        #10 a2_i = 2;  // Read register 2
        #10 a3_i = 3;  // Write register 3
        #10 wd3_i = 32'd12345;  // Write data
        #10 we3_i = 1;  // Enable write
        #10 we3_i = 0;  // Disable write
        // Check the outputs
        if (rd1_o === 32'd0 && rd2_o === 32'd0) $display("Test 1: PASS");
        else $display("Test 1: FAIL");

        // Test 2
        #10 a1_i = 0;  // Read register 0
        #10 a2_i = 4;  // Read register 4
        #10 a3_i = 5;  // Write register 5
        #10 wd3_i = 32'd9876;  // Write data
        #10 we3_i = 1;  // Enable write
        #10 we3_i = 0;  // Disable write
        // Check the outputs
        if (rd1_o === 32'd0 && rd2_o === 32'd0) $display("Test 2: PASS");
        else $display("Test 2: FAIL");

        // Add more tests as needed

        #10 $finish;
    end

    always begin
        #5 clk_i = ~clk_i;
    end
endmodule

test/vcd/register_file.vcd
$date
	Mon Jun 19 16:12:54 2023
$end
$version
	Icarus Verilog
$end
$timescale
	1ps
$end
$scope module register_file_tb $end
$var wire 32 ! rd2_o [31:0] $end
$var wire 32 " rd1_o [31:0] $end
$var reg 5 # a1_i [4:0] $end
$var reg 5 $ a2_i [4:0] $end
$var reg 5 % a3_i [4:0] $end
$var reg 1 & clk_i $end
$var reg 1 ' reset_i $end
$var reg 32 ( wd3_i [31:0] $end
$var reg 1 ) we3_i $end
$scope module dut $end
$var wire 5 * a1_i [4:0] $end
$var wire 5 + a2_i [4:0] $end
$var wire 5 , a3_i [4:0] $end
$var wire 1 & clk_i $end
$var wire 1 ' reset_i $end
$var wire 32 - wd3_i [31:0] $end
$var wire 1 ) we3_i $end
$var reg 32 . rd1_o [31:0] $end
$var reg 32 / rd2_o [31:0] $end
$scope begin $ivl_for_loop0 $end
$var integer 32 0 i [31:0] $end
$upscope $end
$upscope $end
$upscope $end
$enddefinitions $end
$comment Show the parameter values. $end
$dumpall
$end
#0
$dumpvars
bx 0
bx /
bx .
b0 -
b0 ,
b0 +
b0 *
0)
b0 (
1'
0&
b0 %
b0 $
b0 #
bx "
bx !
$end
#5000
b100001 0
1&
#10000
b0 !
b0 /
b0 "
b0 .
0&
0'
#15000
1&
#20000
0&
1'
#25000
b100001 0
1&
#30000
0&
b1 #
b1 *
#35000
b100001 0
1&
#40000
0&
b10 $
b10 +
#45000
b100001 0
1&
#50000
0&
b11 %
b11 ,
#55000
b100001 0
1&
#60000
0&
b11000000111001 (
b11000000111001 -
#65000
b100001 0
1&
#70000
0&
1)
#75000
b100001 0
1&
#80000
0&
0)
#85000
b100001 0
1&
#90000
0&
b0 #
b0 *
#95000
b100001 0
1&
#100000
0&
b100 $
b100 +
#105000
b100001 0
1&
#110000
0&
b101 %
b101 ,
#115000
b100001 0
1&
#120000
0&
b10011010010100 (
b10011010010100 -
#125000
b100001 0
1&
#130000
0&
1)
#135000
b100001 0
1&
#140000
0&
0)
#145000
b100001 0
1&
